kele/__init__.py
kele/_version.py
kele/config.py
kele/egg_equiv.pyi
kele/egg_equiv.so
kele/main.py
kele/py.typed
kele/control/README_metrics.md
kele/control/__init__.py
kele/control/callback.py
kele/control/infer_path.py
kele/control/metrics.py
kele/control/status.py
kele/control/grounding_selector/__init__.py
kele/control/grounding_selector/_selector_utils.py
kele/control/grounding_selector/rule_selector.py
kele/control/grounding_selector/term_selector.py
kele/control/grounding_selector/_rule_strategies/README.md
kele/control/grounding_selector/_rule_strategies/__init__.py
kele/control/grounding_selector/_rule_strategies/_sequential_strategy.py
kele/control/grounding_selector/_rule_strategies/strategy_protocol.py
kele/control/grounding_selector/_term_strategies/__init__.py
kele/control/grounding_selector/_term_strategies/_exhausted_strategy.py
kele/control/grounding_selector/_term_strategies/strategy_protocol.py
kele/equality/README.md
kele/equality/__init__.py
kele/equality/_equiv_elem.py
kele/equality/_utils.py
kele/equality/equivalence.py
kele/equality/_egg_equiv/src/lib.rs
kele/executer/__init__.py
kele/executer/executing.py
kele/grounder/README.md
kele/grounder/__init__.py
kele/grounder/grounding.py
kele/grounder/grounded_rule_ds/__init__.py
kele/grounder/grounded_rule_ds/grounded_class.py
kele/grounder/grounded_rule_ds/grounded_ds_utils.py
kele/grounder/grounded_rule_ds/rule_check.py
kele/grounder/grounded_rule_ds/_nodes/__init__.py
kele/grounder/grounded_rule_ds/_nodes/_assertion.py
kele/grounder/grounded_rule_ds/_nodes/_conn.py
kele/grounder/grounded_rule_ds/_nodes/_op.py
kele/grounder/grounded_rule_ds/_nodes/_root.py
kele/grounder/grounded_rule_ds/_nodes/_rule.py
kele/grounder/grounded_rule_ds/_nodes/_term.py
kele/grounder/grounded_rule_ds/_nodes/_tftable.py
kele/grounder/grounded_rule_ds/_nodes/_tupletable.py
kele/grounder/grounded_rule_ds/_nodes/_typing_polars.py
kele/knowledge_bases/README.md
kele-0.0.1a1.dist-info/METADATA
kele-0.0.1a1.dist-info/WHEEL
kele-0.0.1a1.dist-info/RECORD
kele-0.0.1a1.dist-info/licenses/LICENSE
