Metadata-Version: 2.4
Name: kele
Version: 0.0.1a1
Summary: 推理引擎
Author: Bingqian Li, BoYang Zhang, Weiming Hong, Hao Zhang, Yi Zhou
Maintainer-email: Bingqian Li <libq2022@alumni.shanghaitech.edu.cn>, Yi Zhou <yi_zhou@ustc.edu.cn>
License: BSD-3-Clause
License-File: LICENSE
Requires-Python: <4.0,>=3.13
Requires-Dist: bidict<1.0,>=0.23
Requires-Dist: dacite<2.0,>=1.9
Requires-Dist: graphviz==0.20.3
Requires-Dist: lark<2.0,>=1.0
Requires-Dist: networkx<4.0,>=3.5
Requires-Dist: numpy>=2.3.3
Requires-Dist: polars>=1.32
Requires-Dist: prometheus-client>=0.22
Requires-Dist: psutil>=7.0
Requires-Dist: pydantic<3.0,>=2.0.0
Requires-Dist: python-sat<2.0,>=1.7.dev0
Requires-Dist: pyvis<0.4,>=0.3
Requires-Dist: pyyaml<7.0,>=6.0
Requires-Dist: sympy<2.0,>=1.13
Requires-Dist: tyro<2.0,>=0.9
